{"openweathermap": {"coord": {"lon": 36.8167, "lat": -1.2833}, "weather": [{"id": 500, "main": "Rain", "description": "light rain", "icon": "10n"}], "base": "stations", "main": {"temp": 291.46, "feels_like": 291.64, "temp_min": 291.46, "temp_max": 291.46, "pressure": 1017, "humidity": 88, "sea_level": 1017, "grnd_level": 839}, "visibility": 10000, "wind": {"speed": 2.88, "deg": 44, "gust": 7.45}, "rain": {"1h": 0.4}, "clouds": {"all": 89}, "dt": 1705860949, "sys": {"type": 2, "id": 2006176, "country": "KE", "sunrise": 1705808293, "sunset": 1705852143}, "timezone": 10800, "id": 184745, "name": "Nairobi", "cod": 200}, "weatherstack": {"success": false, "error": {"code": 104, "info": "Your monthly usage limit has been reached. Please upgrade your Subscription Plan."}}, "execution_time": 0.216366}