{"openweathermap": {"coord": {"lon": 36.8167, "lat": -1.2833}, "weather": [{"id": 803, "main": "Clouds", "description": "broken clouds", "icon": "04n"}], "base": "stations", "main": {"temp": 290.91, "feels_like": 291.25, "temp_min": 290.91, "temp_max": 290.91, "pressure": 1016, "humidity": 96, "sea_level": 1016, "grnd_level": 836}, "visibility": 10000, "wind": {"speed": 2.1, "deg": 35, "gust": 4.96}, "clouds": {"all": 65}, "dt": 1703114384, "sys": {"type": 2, "id": 2006176, "country": "KE", "sunrise": 1703129082, "sunset": 1703172983}, "timezone": 10800, "id": 184745, "name": "Nairobi", "cod": 200}, "weatherstack": {"request": {"type": "City", "query": "Nairobi, Kenya", "language": "en", "unit": "m"}, "location": {"name": "Nairobi", "country": "Kenya", "region": "Nairobi Area", "lat": "-1.283", "lon": "36.817", "timezone_id": "Africa/Nairobi", "localtime": "2023-12-21 02:19", "localtime_epoch": 1703125140, "utc_offset": "3.0"}, "current": {"observation_time": "11:19 PM", "temperature": 18, "weather_code": 116, "weather_icons": ["https://cdn.worldweatheronline.com/images/wsymbols01_png_64/wsymbol_0004_black_low_cloud.png"], "weather_descriptions": ["Partly cloudy"], "wind_speed": 4, "wind_degree": 10, "wind_dir": "N", "pressure": 1024, "precip": 0, "humidity": 77, "cloudcover": 75, "feelslike": 18, "uv_index": 1, "visibility": 10, "is_day": "no"}}, "execution_time": 0.420562}