{"openweathermap": {"coord": {"lon": 36.8167, "lat": -1.2833}, "weather": [{"id": 803, "main": "Clouds", "description": "broken clouds", "icon": "04n"}], "base": "stations", "main": {"temp": 291.77, "feels_like": 291.7, "temp_min": 291.77, "temp_max": 293.13, "pressure": 1022, "humidity": 77}, "visibility": 10000, "wind": {"speed": 1.54, "deg": 150}, "clouds": {"all": 75}, "dt": 1705605368, "sys": {"type": 1, "id": 2543, "country": "KE", "sunrise": 1705549032, "sunset": 1705592891}, "timezone": 10800, "id": 184745, "name": "Nairobi", "cod": 200}, "weatherstack": {"request": {"type": "City", "query": "Nairobi, Kenya", "language": "en", "unit": "m"}, "location": {"name": "Nairobi", "country": "Kenya", "region": "Nairobi Area", "lat": "-1.283", "lon": "36.817", "timezone_id": "Africa/Nairobi", "localtime": "2024-01-18 22:15", "localtime_epoch": 1705616100, "utc_offset": "3.0"}, "current": {"observation_time": "07:15 PM", "temperature": 19, "weather_code": 113, "weather_icons": ["https://cdn.worldweatheronline.com/images/wsymbols01_png_64/wsymbol_0008_clear_sky_night.png"], "weather_descriptions": ["Clear"], "wind_speed": 4, "wind_degree": 10, "wind_dir": "N", "pressure": 1023, "precip": 0.1, "humidity": 78, "cloudcover": 0, "feelslike": 19, "uv_index": 1, "visibility": 10, "is_day": "no"}}, "execution_time": 0.359751}